README.md
main.py
setup.py
test.py
rfid2.0.egg-info/PKG-INFO
rfid2.0.egg-info/SOURCES.txt
rfid2.0.egg-info/dependency_links.txt
rfid2.0.egg-info/top_level.txt