Metadata-Version: 2.1
Name: rfid2.0
Version: 2.0.0
Summary: serial库rfid模块整合库
Home-page: 
Author: Liu YUchen
Author-email: liuyuchen032901@outlook.com
